LyScript32/__init__.py
LyScript32-1.0.13.dist-info/LICENSE
LyScript32-1.0.13.dist-info/METADATA
LyScript32-1.0.13.dist-info/WHEEL
LyScript32-1.0.13.dist-info/top_level.txt
LyScript32-1.0.13.dist-info/RECORD
